{
    "title": "crowsetta",
    "url": "https://github.com/vocalpy/crowsetta",
    "description": "package for working with and translating between annotation formats",
    "paidOrFree": "free",
    "codeAvailable": "Y",
    "licenseWipCategory": "BSD",
    "taxonomicOrSoundTypeSpecializationIfAny": null,
    "ecosystemSpecializationIfAny": null,
    "specificHardware": null,
    "type": "Python",
    "dataExploration": null,
    "organization": null,
    "annotation": "port between annotation data types",
    "soundProcessingFeatures": null,
    "acousticParameterMeasurement": null,
    "localization": null,
    "detectorFeatures": null,
    "classifierFeatures": null,
    "removeThisRowBeforePublicationWipCategory": null,
    "comments": null
}