{
    "title": "hybrid-vocal-classifier",
    "url": "https://github.com/vocalpy/hybrid-vocal-classifier",
    "description": "automated labeling geared towards individual syllable identification",
    "paidOrFree": "free",
    "codeAvailable": "Y",
    "licenseWipCategory": "BSD",
    "taxonomicOrSoundTypeSpecializationIfAny": "vocal learning in captive animals",
    "ecosystemSpecializationIfAny": "captive animals",
    "specificHardware": null,
    "type": "Python",
    "dataExploration": null,
    "organization": null,
    "annotation": null,
    "soundProcessingFeatures": null,
    "acousticParameterMeasurement": null,
    "localization": null,
    "detectorFeatures": null,
    "classifierFeatures": "create k-nearest neighbor classifiers for intraspecific individual syllable identification",
    "removeThisRowBeforePublicationWipCategory": null,
    "comments": null
}